LICENSE
MANIFEST.in
README.md
setup.py
docs/Makefile
docs/make.bat
openbte/__init__.py
openbte/almabte2openbte.py
openbte/bte.py
openbte/fourier.py
openbte/geometry.py
openbte/heat_source.py
openbte/material.py
openbte/mesh.py
openbte/objects.py
openbte/utils.py
openbte.egg-info/PKG-INFO
openbte.egg-info/SOURCES.txt
openbte.egg-info/dependency_links.txt
openbte.egg-info/entry_points.txt
openbte.egg-info/requires.txt
openbte.egg-info/top_level.txt
openbte/inverse/bte.py
openbte/inverse/fourier.py
openbte/inverse/matinverse.py
openbte/materials/Si_rta.db