Metadata-Version: 1.1
Name: openbte
Version: 3.0.16
Summary: Boltzmann Transport Equation for Phonons
Home-page: UNKNOWN
Author: Giuseppe Romano
Author-email: romanog@mit.edu
License: GPLv3
Platform: UNKNOWN
Classifier: Programming Language :: Python :: 3.8
